{
  "id": "youth-league-2025",
  "name": "Youth Weekend League",
  "timezone": "America/Toronto",
  "season": {
    "start": "2025-04-01T00:00:00-04:00",
    "end": "2025-06-30T23:59:59-04:00"
  },
  "entities": {
    "teams": [
      { "id": "U12-A", "name": "U12 Team A" },
      { "id": "U12-B", "name": "U12 Team B" }
    ],
    "venues": [
      { "id": "park-1", "name": "Community Park 1" }
    ]
  },
  "fixtures": [
    {
      "id": "match-1",
      "participants": ["U12-A", "U12-B"],
      "durationMinutes": 60
    }
  ],
  "constraints": [
    {
      "id": "no_overlap_team",
      "type": "hard",
      "rule": "no_overlap_team",
      "selector": { "entityType": "team" }
    },
    {
      "id": "weekend_only",
      "type": "hard",
      "rule": "time_window",
      "selector": { "entityType": "fixture" },
      "params": {
        "allowed_days": ["Saturday", "Sunday"]
      }
    },
    {
      "id": "minimize_travel",
      "type": "soft",
      "rule": "minimize_travel",
      "selector": { "entityType": "team" },
      "penalty": { "model": "linear", "weight": 1.0 }
    }
  ],
  "objectives": [
    {
      "metric": "total_travel_distance",
      "aggregation": "sum",
      "weight": 1.0
    }
  ]
}
